README.md
setup.py
om_vlp/__init__.py
om_vlp/engine.py
om_vlp.egg-info/PKG-INFO
om_vlp.egg-info/SOURCES.txt
om_vlp.egg-info/dependency_links.txt
om_vlp.egg-info/requires.txt
om_vlp.egg-info/top_level.txt
om_vlp/configs/__init__.py
om_vlp/model/__init__.py
om_vlp/model/builder.py
om_vlp/model/modules.py
om_vlp/model/utils.py
om_vlp/model/wukong.py
om_vlp/model/language/__init__.py
om_vlp/model/language/transformer.py
om_vlp/model/vision/__init__.py
om_vlp/model/vision/swin_transformer.py
om_vlp/model/vision/vision_transformer.py
om_vlp/tokenizer/__init__.py
om_vlp/tokenizer/simple_tokenizer.py