Metadata-Version: 2.1
Name: om-vlp
Version: 0.0.2
Summary: VLP models
Home-page: https://www.soco.ai
Author: kyusonglee
License: UNKNOWN
Platform: UNKNOWN
Classifier: Programming Language :: Python :: 3
Classifier: License :: Free for non-commercial use
Classifier: Operating System :: OS Independent
